[
  {
    "id": "af",
    "value": "Afrikaans"
  },
  {
    "id": "sq",
    "value": "Albanian"
  },
  {
    "id": "am",
    "value": "Amharic"
  },
  {
    "id": "ar",
    "value": "Arabic"
  },
  {
    "id": "hy",
    "value": "Armenian"
  },
  {
    "id": "as",
    "value": "Assamese"
  },
  {
    "id": "ay",
    "value": "Aymara"
  },
  {
    "id": "az",
    "value": "Azerbaijani"
  },
  {
    "id": "bm",
    "value": "Bambara"
  },
  {
    "id": "eu",
    "value": "Basque"
  },
  {
    "id": "be",
    "value": "Belarusian"
  },
  {
    "id": "bn",
    "value": "Bengali"
  },
  {
    "id": "bho",
    "value": "Bhojpuri"
  },
  {
    "id": "bs",
    "value": "Bosnian"
  },
  {
    "id": "bg",
    "value": "Bulgarian"
  },
  {
    "id": "ca",
    "value": "Catalan"
  },
  {
    "id": "ceb",
    "value": "Cebuano"
  },
  {
    "id": "ny",
    "value": "Chichewa"
  },
  {
    "id": "zh-CN",
    "value": "Chinese (Simplified)"
  },
  {
    "id": "zh-TW",
    "value": "Chinese (Traditional)"
  },
  {
    "id": "co",
    "value": "Corsican"
  },
  {
    "id": "hr",
    "value": "Croatian"
  },
  {
    "id": "cs",
    "value": "Czech"
  },
  {
    "id": "da",
    "value": "Danish"
  },
  {
    "id": "dv",
    "value": "Dhivehi"
  },
  {
    "id": "doi",
    "value": "Dogri"
  },
  {
    "id": "nl",
    "value": "Dutch"
  },
  {
    "id": "en",
    "value": "English"
  },
  {
    "id": "eo",
    "value": "Esperanto"
  },
  {
    "id": "et",
    "value": "Estonian"
  },
  {
    "id": "ee",
    "value": "Ewe"
  },
  {
    "id": "tl",
    "value": "Filipino"
  },
  {
    "id": "fi",
    "value": "Finnish"
  },
  {
    "id": "fr",
    "value": "French"
  },
  {
    "id": "fy",
    "value": "Frisian"
  },
  {
    "id": "gl",
    "value": "Galician"
  },
  {
    "id": "ka",
    "value": "Georgian"
  },
  {
    "id": "de",
    "value": "German"
  },
  {
    "id": "el",
    "value": "Greek"
  },
  {
    "id": "gn",
    "value": "Guarani"
  },
  {
    "id": "gu",
    "value": "Gujarati"
  },
  {
    "id": "ht",
    "value": "Haitian Creole"
  },
  {
    "id": "ha",
    "value": "Hausa"
  },
  {
    "id": "haw",
    "value": "Hawaiian"
  },
  {
    "id": "iw",
    "value": "Hebrew"
  },
  {
    "id": "hi",
    "value": "Hindi"
  },
  {
    "id": "hmn",
    "value": "Hmong"
  },
  {
    "id": "hu",
    "value": "Hungarian"
  },
  {
    "id": "is",
    "value": "Icelandic"
  },
  {
    "id": "ig",
    "value": "Igbo"
  },
  {
    "id": "ilo",
    "value": "Ilocano"
  },
  {
    "id": "id",
    "value": "Indonesian"
  },
  {
    "id": "ga",
    "value": "Irish"
  },
  {
    "id": "it",
    "value": "Italian"
  },
  {
    "id": "ja",
    "value": "Japanese"
  },
  {
    "id": "jw",
    "value": "Javanese"
  },
  {
    "id": "kn",
    "value": "Kannada"
  },
  {
    "id": "kk",
    "value": "Kazakh"
  },
  {
    "id": "km",
    "value": "Khmer"
  },
  {
    "id": "rw",
    "value": "Kinyarwanda"
  },
  {
    "id": "gom",
    "value": "Konkani"
  },
  {
    "id": "ko",
    "value": "Korean"
  },
  {
    "id": "kri",
    "value": "Krio"
  },
  {
    "id": "ku",
    "value": "Kurdish (Kurmanji)"
  },
  {
    "id": "ckb",
    "value": "Kurdish (Sorani)"
  },
  {
    "id": "ky",
    "value": "Kyrgyz"
  },
  {
    "id": "lo",
    "value": "Lao"
  },
  {
    "id": "la",
    "value": "Latin"
  },
  {
    "id": "lv",
    "value": "Latvian"
  },
  {
    "id": "ln",
    "value": "Lingala"
  },
  {
    "id": "lt",
    "value": "Lithuanian"
  },
  {
    "id": "lg",
    "value": "Luganda"
  },
  {
    "id": "lb",
    "value": "Luxembourgish"
  },
  {
    "id": "mk",
    "value": "Macedonian"
  },
  {
    "id": "mai",
    "value": "Maithili"
  },
  {
    "id": "mg",
    "value": "Malagasy"
  },
  {
    "id": "ms",
    "value": "Malay"
  },
  {
    "id": "ml",
    "value": "Malayalam"
  },
  {
    "id": "mt",
    "value": "Maltese"
  },
  {
    "id": "mi",
    "value": "Maori"
  },
  {
    "id": "mr",
    "value": "Marathi"
  },
  {
    "id": "mni-Mtei",
    "value": "Meiteilon (Manipuri)"
  },
  {
    "id": "lus",
    "value": "Mizo"
  },
  {
    "id": "mn",
    "value": "Mongolian"
  },
  {
    "id": "my",
    "value": "Myanmar (Burmese)"
  },
  {
    "id": "ne",
    "value": "Nepali"
  },
  {
    "id": "no",
    "value": "Norwegian"
  },
  {
    "id": "or",
    "value": "Odia (Oriya)"
  },
  {
    "id": "om",
    "value": "Oromo"
  },
  {
    "id": "ps",
    "value": "Pashto"
  },
  {
    "id": "fa",
    "value": "Persian"
  },
  {
    "id": "pl",
    "value": "Polish"
  },
  {
    "id": "pt",
    "value": "Portuguese"
  },
  {
    "id": "pa",
    "value": "Punjabi"
  },
  {
    "id": "qu",
    "value": "Quechua"
  },
  {
    "id": "ro",
    "value": "Romanian"
  },
  {
    "id": "ru",
    "value": "Russian"
  },
  {
    "id": "sm",
    "value": "Samoan"
  },
  {
    "id": "sa",
    "value": "Sanskrit"
  },
  {
    "id": "gd",
    "value": "Scots Gaelic"
  },
  {
    "id": "nso",
    "value": "Sepedi"
  },
  {
    "id": "sr",
    "value": "Serbian"
  },
  {
    "id": "st",
    "value": "Sesotho"
  },
  {
    "id": "sn",
    "value": "Shona"
  },
  {
    "id": "sd",
    "value": "Sindhi"
  },
  {
    "id": "si",
    "value": "Sinhala"
  },
  {
    "id": "sk",
    "value": "Slovak"
  },
  {
    "id": "sl",
    "value": "Slovenian"
  },
  {
    "id": "so",
    "value": "Somali"
  },
  {
    "id": "es",
    "value": "Spanish"
  },
  {
    "id": "su",
    "value": "Sundanese"
  },
  {
    "id": "sw",
    "value": "Swahili"
  },
  {
    "id": "sv",
    "value": "Swedish"
  },
  {
    "id": "tg",
    "value": "Tajik"
  },
  {
    "id": "ta",
    "value": "Tamil"
  },
  {
    "id": "tt",
    "value": "Tatar"
  },
  {
    "id": "te",
    "value": "Telugu"
  },
  {
    "id": "th",
    "value": "Thai"
  },
  {
    "id": "ti",
    "value": "Tigrinya"
  },
  {
    "id": "ts",
    "value": "Tsonga"
  },
  {
    "id": "tr",
    "value": "Turkish"
  },
  {
    "id": "tk",
    "value": "Turkmen"
  },
  {
    "id": "ak",
    "value": "Twi"
  },
  {
    "id": "uk",
    "value": "Ukrainian"
  },
  {
    "id": "ur",
    "value": "Urdu"
  },
  {
    "id": "ug",
    "value": "Uyghur"
  },
  {
    "id": "uz",
    "value": "Uzbek"
  },
  {
    "id": "vi",
    "value": "Vietnamese"
  },
  {
    "id": "cy",
    "value": "Welsh"
  },
  {
    "id": "xh",
    "value": "Xhosa"
  },
  {
    "id": "yi",
    "value": "Yiddish"
  },
  {
    "id": "yo",
    "value": "Yoruba"
  },
  {
    "id": "zu",
    "value": "Zulu"
  }
]
